{
  "model_name": "xgboost",
  "metrics": {
    "rmse": 19.779000354491686,
    "mae": 15.79975523423711,
    "r2": 0.46152807191668,
    "mape": 20.114528698199894,
    "train_r2": 0.6808810865712075,
    "overfitting_gap": 0.2193530146545275
  },
  "feature_names": [
    "temperature",
    "humidity",
    "wind_speed",
    "wind_direction",
    "pressure",
    "hour",
    "day_of_week",
    "day_of_month",
    "month",
    "quarter",
    "is_weekend",
    "hour_sin",
    "hour_cos",
    "day_of_week_sin",
    "day_of_week_cos",
    "month_sin",
    "month_cos",
    "aqi_lag_1h",
    "aqi_lag_3h",
    "aqi_lag_6h",
    "aqi_lag_12h",
    "aqi_lag1",
    "aqi_change",
    "aqi_change_rate",
    "aqi_rolling_mean_6h",
    "aqi_rolling_std_6h",
    "aqi_rolling_max_6h",
    "aqi_rolling_min_6h",
    "aqi_rolling_mean_12h",
    "aqi_rolling_std_12h",
    "aqi_rolling_max_12h",
    "aqi_rolling_min_12h",
    "aqi_rolling_mean_24h",
    "aqi_rolling_std_24h",
    "aqi_rolling_max_24h",
    "aqi_rolling_min_24h",
    "aqi_rolling_mean_48h",
    "aqi_rolling_std_48h",
    "aqi_rolling_max_48h",
    "aqi_rolling_min_48h",
    "aqi_ema_6h",
    "aqi_ema_12h",
    "aqi_ema_24h",
    "heat_index",
    "comfort_index",
    "wind_speed_squared",
    "pm25",
    "pm10",
    "no2",
    "o3",
    "pm25_aqi",
    "pm10_aqi",
    "o3_aqi",
    "no2_aqi",
    "aqi_calculated",
    "pm25_pm10_ratio"
  ],
  "trained_at": "2026-01-17T03:06:02.897951",
  "version": "1.0"
}